stringzilla.cp312-win_amd64.pyd
cli/__init__.py
cli/split.py
cli/wc.py
stringzilla-4.6.0.dist-info/licenses/LICENSE
stringzilla-4.6.0.dist-info/METADATA
stringzilla-4.6.0.dist-info/WHEEL
stringzilla-4.6.0.dist-info/entry_points.txt
stringzilla-4.6.0.dist-info/top_level.txt
stringzilla-4.6.0.dist-info/RECORD
